TUI_pygame/__init__.py
tui_pygame-0.1.3.dist-info/METADATA
tui_pygame-0.1.3.dist-info/WHEEL
tui_pygame-0.1.3.dist-info/top_level.txt
tui_pygame-0.1.3.dist-info/RECORD
