Metadata-Version: 2.4
Name: TUI_pygame
Version: 0.1.3
Summary: A library for implementing something similar to Pygame in the command line.
Author-email: liujunyi <liujunyi0702@petalmail.com>
License: MIT
Classifier: Programming Language :: Python :: 3
Classifier: License :: OSI Approved :: MIT License
Classifier: Operating System :: OS Independent
Requires-Python: >=3.0
